scTrace/__init__.py
scTrace/pipeline.py
scTrace/scLTMF.py
scTrace/utils.py
scTrace-0.1.7.dist-info/METADATA
scTrace-0.1.7.dist-info/WHEEL
scTrace-0.1.7.dist-info/top_level.txt
scTrace-0.1.7.dist-info/RECORD
